pyautosrt/__init__.py
test/__init__.py
pyautosrt-0.2.9.dist-info/METADATA
pyautosrt-0.2.9.dist-info/WHEEL
pyautosrt-0.2.9.dist-info/entry_points.txt
pyautosrt-0.2.9.dist-info/top_level.txt
pyautosrt-0.2.9.dist-info/RECORD
