Metadata-Version: 2.1
Name: pyautosrt
Version: 0.2.9
Summary: pyautosrt is a python based desktop app to generate subtitle and translated subtitle file
Home-page: https://github.com/botbahlul/pyautosrt
Author: Bot Bahlul
Author-email: bot.bahlul@gmail.com
License: MIT License
Requires-Dist: requests (>=2.3.0)
Requires-Dist: httpx (>=0.13.3)
Requires-Dist: pysrt (>=1.0.1)
Requires-Dist: six (>=1.11.0)
Requires-Dist: pysimplegui (>=4.60.1)
Requires-Dist: streamlink (>=5.3.1)
Requires-Dist: urllib3 (<3.0,>=1.26.0)
